setup.py
load_resources/__init__.py
load_resources/load_resources.py
load_resources.egg-info/PKG-INFO
load_resources.egg-info/SOURCES.txt
load_resources.egg-info/dependency_links.txt
load_resources.egg-info/top_level.txt