Metadata-Version: 1.1
Name: load-resources
Version: 0.11
Summary: A simple util to load all resources from a given directory into a dictionary
Home-page: https://github.com/fiebiga/load_resources
Author: Adam Fiebig
Author-email: fiebig.adam@gmail.com
License: UNKNOWN
Download-URL: https://github.com/fiebiga/load_resources/tarball/master
Platform: Linux
Classifier: Development Status :: 5 - Production/Stable
Classifier: License :: OSI Approved :: GNU General Public License v3 or later (GPLv3+)
Classifier: Programming Language :: Python
Classifier: Programming Language :: Python :: 2
Classifier: Programming Language :: Python :: 2.7
Classifier: Programming Language :: Python :: 3.3
Classifier: Programming Language :: Python :: Implementation :: PyPy
Classifier: Intended Audience :: Developers
Classifier: Intended Audience :: System Administrators
